xparse_pipeline/__init__.py
xparse_pipeline/core.py
xparse_pipeline-0.1.7.dist-info/licenses/LICENSE
xparse_pipeline-0.1.7.dist-info/METADATA
xparse_pipeline-0.1.7.dist-info/WHEEL
xparse_pipeline-0.1.7.dist-info/top_level.txt
xparse_pipeline-0.1.7.dist-info/RECORD
