Metadata-Version: 2.4
Name: xparse-pipeline
Version: 0.1.7
Summary: Xparse 数据处理 Pipeline
License-Expression: MIT
Project-URL: Homepage, https://gitlab.intsig.net/xparse1/xparse-pipeline
Project-URL: Repository, https://gitlab.intsig.net/xparse1/xparse-pipeline
Keywords: xparse,pipeline,rag
Requires-Python: >=3.8
License-File: LICENSE
Requires-Dist: boto3
Requires-Dist: pymilvus[milvus_lite]
Requires-Dist: requests
Dynamic: license-file
